MANIFEST.in
README.rst
setup.py
wr.py
wr.egg-info/PKG-INFO
wr.egg-info/SOURCES.txt
wr.egg-info/dependency_links.txt
wr.egg-info/top_level.txt
wr.egg-info/zip-safe